MANIFEST.in
README.rst
setup.py
bin/pydigger
pydigger/__init__.py
pydigger/implementation.py
pydigger.egg-info/PKG-INFO
pydigger.egg-info/SOURCES.txt
pydigger.egg-info/dependency_links.txt
pydigger.egg-info/not-zip-safe
pydigger.egg-info/top_level.txt