Metadata-Version: 1.1
Name: pydigger
Version: 0.1
Summary: Diggin Py
Home-page: http://github.com/szabgab/pyd
Author: Gabor Szabo
Author-email: gabor@szabgab.com
License: MIT
Platform: UNKNOWN
Requires: lawyerup
